bpcmp/__init__.py
bpcmp/bpcmp.py
bpcmp/bpdump.py
bpcmp-1.1.0.dist-info/LICENSE
bpcmp-1.1.0.dist-info/METADATA
bpcmp-1.1.0.dist-info/WHEEL
bpcmp-1.1.0.dist-info/entry_points.txt
bpcmp-1.1.0.dist-info/top_level.txt
bpcmp-1.1.0.dist-info/RECORD
