Metadata-Version: 2.2
Name: bpcmp
Version: 1.1.0
Summary: Comparison tool for ADIOS2 bp output
Author-email: Jai Sachdev <jsachdev@pppl.gov>
License: GNU General Public License 3
Keywords: ADIOS2,comparison,regression testing
Classifier: Programming Language :: Python :: 3
Requires-Python: >=3.10
License-File: LICENSE
Requires-Dist: setuptools-scm
Requires-Dist: numpy
Requires-Dist: adios2
Requires-Dist: termcolor
Provides-Extra: dev
Requires-Dist: autopep8; extra == "dev"
Requires-Dist: flake8; extra == "dev"
Provides-Extra: docs
Requires-Dist: sphinx; extra == "docs"
Requires-Dist: sphinx_rtd_theme; extra == "docs"
Requires-Dist: readthedocs-sphinx-search; extra == "docs"
Requires-Dist: sphinx-autobuild; extra == "docs"
